[
    {
        "icon": "/images/icons/question.png",
        "title": "Help & more",
        "links": [
            {
                "id": 1,
                "link": "http://localhost:5173",
                "text": "Contact us"
            },
            {
                "id": 2,
                "link": "http://localhost:5173",
                "text": "Returns"
            },
            {
                "id": 3,
                "link": "http://localhost:5173",
                "text": "EU delivery"
            }
        ]
    },
    {
        "icon": "/images/icons/bag.png",
        "title": "Products",
        "links": [
            {
                "id": 4,
                "link": "http://localhost:5173",
                "text": "Casual"
            },
            {
                "id": 5,
                "link": "http://localhost:5173",
                "text": "Men"
            },
            {
                "id": 6,
                "link": "http://localhost:5173",
                "text": "Women"
            }
        ]
    },
    {
        "icon": "/images/icons/shop.png",
        "title": "iBuy Group",
        "links": [
            {
                "id": 7,
                "link": "http://localhost:5173",
                "text": "Career"
            },
            {
                "id": 8,
                "link": "http://localhost:5173",
                "text": "About us"
            },
            {
                "id": 9,
                "link": "http://localhost:5173",
                "text": "iBuy group international"
            }
        ]
    }
]